README.md
setup.py
pulumiverse_fortios/__init__.py
pulumiverse_fortios/_utilities.py
pulumiverse_fortios/provider.py
pulumiverse_fortios/pulumi-plugin.json
pulumiverse_fortios/py.typed
pulumiverse_fortios.egg-info/PKG-INFO
pulumiverse_fortios.egg-info/SOURCES.txt
pulumiverse_fortios.egg-info/dependency_links.txt
pulumiverse_fortios.egg-info/not-zip-safe
pulumiverse_fortios.egg-info/requires.txt
pulumiverse_fortios.egg-info/top_level.txt
pulumiverse_fortios/alertemail/__init__.py
pulumiverse_fortios/alertemail/setting.py
pulumiverse_fortios/antivirus/__init__.py
pulumiverse_fortios/antivirus/_inputs.py
pulumiverse_fortios/antivirus/exemptlist.py
pulumiverse_fortios/antivirus/heuristic.py
pulumiverse_fortios/antivirus/outputs.py
pulumiverse_fortios/antivirus/profile.py
pulumiverse_fortios/antivirus/quarantine.py
pulumiverse_fortios/antivirus/settings.py
pulumiverse_fortios/application/__init__.py
pulumiverse_fortios/application/_inputs.py
pulumiverse_fortios/application/custom.py
pulumiverse_fortios/application/group.py
pulumiverse_fortios/application/list.py
pulumiverse_fortios/application/name.py
pulumiverse_fortios/application/outputs.py
pulumiverse_fortios/application/rulesettings.py
pulumiverse_fortios/authentication/__init__.py
pulumiverse_fortios/authentication/_inputs.py
pulumiverse_fortios/authentication/outputs.py
pulumiverse_fortios/authentication/rule.py
pulumiverse_fortios/authentication/scheme.py
pulumiverse_fortios/authentication/setting.py
pulumiverse_fortios/automation/__init__.py
pulumiverse_fortios/automation/setting.py
pulumiverse_fortios/casb/__init__.py
pulumiverse_fortios/casb/_inputs.py
pulumiverse_fortios/casb/outputs.py
pulumiverse_fortios/casb/profile.py
pulumiverse_fortios/casb/saasapplication.py
pulumiverse_fortios/casb/useractivity.py
pulumiverse_fortios/certificate/__init__.py
pulumiverse_fortios/certificate/ca.py
pulumiverse_fortios/certificate/crl.py
pulumiverse_fortios/certificate/local.py
pulumiverse_fortios/certificate/remote.py
pulumiverse_fortios/cifs/__init__.py
pulumiverse_fortios/cifs/_inputs.py
pulumiverse_fortios/cifs/domaincontroller.py
pulumiverse_fortios/cifs/outputs.py
pulumiverse_fortios/cifs/profile.py
pulumiverse_fortios/config/__init__.py
