Metadata-Version: 2.1
Name: pulumiverse-fortios
Version: 0.0.6
Summary: A Pulumi package for creating and managing Fortios resources
Home-page: https://github.com/pulumiverse/pulumi-fortios
License: Apache-2.0
Project-URL: Repository, https://github.com/pulumiverse/pulumi-fortios
Keywords: pulumi fortios category/cloud
Platform: UNKNOWN
Requires-Python: >=3.8
